alibi_detect/__init__.py
alibi_detect/base.py
alibi_detect/datasets.py
alibi_detect/exceptions.py
alibi_detect/version.py
alibi_detect/ad/__init__.py
alibi_detect/ad/adversarialae.py
alibi_detect/ad/model_distillation.py
alibi_detect/cd/__init__.py
alibi_detect/cd/_domain_clf.py
alibi_detect/cd/base.py
alibi_detect/cd/base_online.py
alibi_detect/cd/chisquare.py
alibi_detect/cd/classifier.py
alibi_detect/cd/context_aware.py
alibi_detect/cd/cvm.py
alibi_detect/cd/cvm_online.py
alibi_detect/cd/fet.py
alibi_detect/cd/fet_online.py
alibi_detect/cd/ks.py
alibi_detect/cd/learned_kernel.py
alibi_detect/cd/lsdd.py
alibi_detect/cd/lsdd_online.py
alibi_detect/cd/mmd.py
alibi_detect/cd/mmd_online.py
alibi_detect/cd/model_uncertainty.py
alibi_detect/cd/preprocess.py
alibi_detect/cd/spot_the_diff.py
alibi_detect/cd/tabular.py
alibi_detect/cd/utils.py
alibi_detect/cd/keops/__init__.py
alibi_detect/cd/keops/learned_kernel.py
alibi_detect/cd/keops/mmd.py
alibi_detect/cd/pytorch/__init__.py
alibi_detect/cd/pytorch/classifier.py
alibi_detect/cd/pytorch/context_aware.py
alibi_detect/cd/pytorch/learned_kernel.py
alibi_detect/cd/pytorch/lsdd.py
alibi_detect/cd/pytorch/lsdd_online.py
alibi_detect/cd/pytorch/mmd.py
alibi_detect/cd/pytorch/mmd_online.py
alibi_detect/cd/pytorch/preprocess.py
alibi_detect/cd/pytorch/spot_the_diff.py
alibi_detect/cd/pytorch/utils.py
alibi_detect/cd/sklearn/__init__.py
alibi_detect/cd/sklearn/classifier.py
alibi_detect/cd/tensorflow/__init__.py
alibi_detect/cd/tensorflow/classifier.py
alibi_detect/cd/tensorflow/context_aware.py
alibi_detect/cd/tensorflow/learned_kernel.py
alibi_detect/cd/tensorflow/lsdd.py
alibi_detect/cd/tensorflow/lsdd_online.py
alibi_detect/cd/tensorflow/mmd.py
alibi_detect/cd/tensorflow/mmd_online.py
alibi_detect/cd/tensorflow/preprocess.py
alibi_detect/cd/tensorflow/spot_the_diff.py
alibi_detect/cd/tensorflow/utils.py
alibi_detect/models/__init__.py
alibi_detect/models/pytorch/__init__.py
alibi_detect/models/pytorch/embedding.py
alibi_detect-0.13.0.dist-info/licenses/LICENSE
alibi_detect-0.13.0.dist-info/METADATA
alibi_detect-0.13.0.dist-info/WHEEL
alibi_detect-0.13.0.dist-info/entry_points.txt
alibi_detect-0.13.0.dist-info/top_level.txt
alibi_detect-0.13.0.dist-info/RECORD
